README.md
setup.py
flask_bootframe/App.py
flask_bootframe/__init__.py
flask_bootframe/conventions.py
flask_bootframe.egg-info/PKG-INFO
flask_bootframe.egg-info/SOURCES.txt
flask_bootframe.egg-info/dependency_links.txt
flask_bootframe.egg-info/requires.txt
flask_bootframe.egg-info/top_level.txt
flask_bootframe/AppFactory/__init__.py
flask_bootframe/AppFactory/basic.py
flask_bootframe/AppFactory/http.py
flask_bootframe/AppFactory/websocket.py
flask_bootframe/ConfigContainer/__init__.py
flask_bootframe/Scanner/__init__.py
flask_bootframe/Scanner/load.py
flask_bootframe/Scanner/scan.py
flask_bootframe/core/__init__.py
flask_bootframe/core/Basics/__init__.py
flask_bootframe/core/Basics/config.py
flask_bootframe/core/Basics/controller.py
flask_bootframe/core/Basics/interaction.py
flask_bootframe/core/Basics/servlet.py
flask_bootframe/core/Exception/Exceptions.py
flask_bootframe/core/Exception/__init__.py
flask_bootframe/core/Exception/handler.py
flask_bootframe/core/servlet/BootMiddleWare.py
flask_bootframe/core/servlet/__init__.py
flask_bootframe/default/__init__.py
flask_bootframe/default/config/ServletConfig.py
flask_bootframe/default/config/SwaggerConfig.py
flask_bootframe/default/config/__init__.py
flask_bootframe/default/controller/PluginHttpController.py
flask_bootframe/default/controller/TestHttpControllerFactory.py
flask_bootframe/default/controller/__init__.py
flask_bootframe/default/dao/PluginDao.py
flask_bootframe/default/dao/__init__.py
flask_bootframe/default/entity/__init__.py
flask_bootframe/default/entity/do/Plugin.py
flask_bootframe/default/entity/do/__init__.py
flask_bootframe/default/router/PluginHttpRouter.py
flask_bootframe/default/router/TestHttpRouter.py
flask_bootframe/default/router/__init__.py
flask_bootframe/default/service/PluginServiceInterface.py
flask_bootframe/default/service/__init__.py
flask_bootframe/default/service/Impl/PluginServiceImpl.py
flask_bootframe/default/service/Impl/__init__.py
flask_bootframe/side/BasicSide.py
flask_bootframe/side/PluginSide.py
flask_bootframe/side/TestSide.py
flask_bootframe/side/__init__.py