Metadata-Version: 2.1
Name: flask-bootframe
Version: 1.0
Summary:  a flask boot framework both Win and Mac 
Home-page: https://github.com/ababbabbb/programme/tree/master/topics/backend/netapis/netapi_flask/flask_boot
Author: bichuantao
Author-email: 17826066203@163.com
License: MIT
Keywords: python,flask,boot,framework
Classifier: Development Status :: 3 - Alpha
Classifier: Intended Audience :: Developers
Classifier: Topic :: Software Development :: Build Tools
Classifier: License :: OSI Approved :: MIT License
Classifier: Programming Language :: Python :: 3.6
Classifier: Programming Language :: Python :: 3.7
Classifier: Programming Language :: Python :: 3.8
Classifier: Programming Language :: Python :: 3.9
